pygments_promql/__init__.py
pygments_promql-0.1.1.dist-info/LICENSE
pygments_promql-0.1.1.dist-info/METADATA
pygments_promql-0.1.1.dist-info/WHEEL
pygments_promql-0.1.1.dist-info/entry_points.txt
pygments_promql-0.1.1.dist-info/top_level.txt
pygments_promql-0.1.1.dist-info/RECORD
