Metadata-Version: 2.1
Name: pygments-promql
Version: 0.1.1
Summary: A PromQL lexer for Pygments
Home-page: https://github.com/pabluk/pygments-promql
Author: Pablo Seminario
Author-email: pablo@seminar.io
Keywords: pygments-lexer promql highlighting
Classifier: Programming Language :: Python :: 3
Classifier: License :: OSI Approved :: BSD License
Classifier: Operating System :: OS Independent
Classifier: Topic :: Text Processing
Classifier: Topic :: Utilities
Requires-Python: >=3.7
License-File: LICENSE
Requires-Dist: Pygments >=2
